superposition_theorem/__init__.py
superposition_theorem/main.py
superposition_theorem/core/__init__.py
superposition_theorem/core/compute_beta_coefficients.py
superposition_theorem/core/compute_power_flows.py
superposition_theorem/tests/__init__.py
superposition_theorem/tests/test_different_action_type_superposition.py
superposition_theorem/tests/test_line_disconnection_superposition.py
superposition_theorem/tests/test_line_reconnection_superposition.py
superposition_theorem/tests/test_node_merging_superposition.py
superposition_theorem/tests/test_node_splitting_superposition.py
TopologySuperpositionTheorem-0.0.2.dist-info/LICENSE.md
TopologySuperpositionTheorem-0.0.2.dist-info/METADATA
TopologySuperpositionTheorem-0.0.2.dist-info/WHEEL
TopologySuperpositionTheorem-0.0.2.dist-info/top_level.txt
TopologySuperpositionTheorem-0.0.2.dist-info/RECORD
