Metadata-Version: 2.1
Name: TopologySuperpositionTheorem
Version: 0.0.2
Summary: A package for efficient combinatorial topological actions power flow computation based on the extended superposition theorem for powersystems
Home-page: https://github.com/marota/Topology_Superposition_Theorem
Author: Antoine MAROT
License: Mozilla Public License 2.0 (MPL 2.0)
Keywords: combinatorial powerflow topology power-systems
Classifier: Development Status :: 4 - Beta
Classifier: Programming Language :: Python :: 3.7
Classifier: Programming Language :: Python :: 3.8
Classifier: Programming Language :: Python :: 3.9
Classifier: Programming Language :: Python :: 3.10
Classifier: Programming Language :: Python :: 3.11
Classifier: License :: OSI Approved :: Mozilla Public License 2.0 (MPL 2.0)
Classifier: Intended Audience :: Developers
Classifier: Intended Audience :: Education
Classifier: Intended Audience :: Science/Research
Classifier: Natural Language :: English
Classifier: Operating System :: MacOS
Classifier: Operating System :: Microsoft :: Windows
Classifier: Operating System :: POSIX
Classifier: Topic :: Scientific/Engineering
Requires-Python: >=3.8
License-File: LICENSE.md
Requires-Dist: grid2op (>=1.9)
Requires-Dist: lightsim2grid (>=0.7)
